stackblur.py
cstackblur.cpython-310-x86_64-linux-gnu.so
pillow_stackblur-0.1.1.dist-info/top_level.txt
pillow_stackblur-0.1.1.dist-info/RECORD
pillow_stackblur-0.1.1.dist-info/WHEEL
pillow_stackblur-0.1.1.dist-info/METADATA
