Metadata-Version: 2.1
Name: pillow-stackblur
Version: 0.1.1
Summary: The Pillow filter for Stack Blur.
Home-page: https://github.com/dldevinc/pillow-stackblur
Author: Jones Chi
Author-email: duguschi@gmail.com
License: MIT
Requires-Python: >=3.5.0
Requires-Dist: pillow
Provides-Extra: optional
